thebestbestttlibeve/__inint__.py
thebestbestttlibeve/fibonacci.py
thebestbestttlibeve/main.py
thebestbestttlibeve/visitor.py
thebestbestttlibever-0.5.dist-info/LICENSE
thebestbestttlibever-0.5.dist-info/METADATA
thebestbestttlibever-0.5.dist-info/WHEEL
thebestbestttlibever-0.5.dist-info/top_level.txt
thebestbestttlibever-0.5.dist-info/RECORD
